llm_lite.py
llm_litellm-0.2.0.dist-info/licenses/LICENSE
llm_litellm-0.2.0.dist-info/METADATA
llm_litellm-0.2.0.dist-info/WHEEL
llm_litellm-0.2.0.dist-info/entry_points.txt
llm_litellm-0.2.0.dist-info/top_level.txt
llm_litellm-0.2.0.dist-info/RECORD
