Metadata-Version: 2.4
Name: llm-litellm
Version: 0.2.0
Summary: LLM plugin for LiteLLM proxy server
Author: Rajashekar Chintalapati
License: Apache-2.0
Project-URL: Homepage, https://github.com/rajashekar/llm-litellm
Project-URL: Changelog, https://github.com/rajashekar/llm-litellm/releases
Project-URL: Issues, https://github.com/rajashekar/llm-litellm/issues
Project-URL: CI, https://github.com/rajashekar/llm-litellm/actions
Keywords: llm,ai,litellm,language-models,plugin
Classifier: Development Status :: 3 - Alpha
Classifier: Intended Audience :: Developers
Classifier: License :: OSI Approved :: Apache Software License
Classifier: Programming Language :: Python :: 3
Classifier: Programming Language :: Python :: 3.8
Classifier: Programming Language :: Python :: 3.9
Classifier: Programming Language :: Python :: 3.10
Classifier: Programming Language :: Python :: 3.11
Classifier: Programming Language :: Python :: 3.12
Classifier: Topic :: Software Development :: Libraries :: Python Modules
Requires-Python: >=3.8
License-File: LICENSE
Requires-Dist: llm>=0.13
Requires-Dist: httpx
Requires-Dist: openai>=1.0.0
Provides-Extra: test
Requires-Dist: pytest; extra == "test"
Requires-Dist: pytest-mock; extra == "test"
Requires-Dist: flake8; extra == "test"
Dynamic: license-file
